{"id":26998,"title":"Peter Pan in Kensington Gardens","authors":[{"name":"Barrie, J. M. (James Matthew)","birth_year":1860,"death_year":1937}],"translators":[],"subjects":["Fairies -- Fiction","Fantasy literature","Kensington Gardens (London, England) -- Fiction","Peter Pan (Fictitious character) -- Fiction"],"bookshelves":[],"languages":["en"],"copyright":false,"media_type":"Text","formats":{"application/zip":"https://www.gutenberg.org/files/26998/26998.zip","text/plain; charset=us-ascii":"https://www.gutenberg.org/files/26998/26998.txt","text/html; charset=iso-8859-1":"https://www.gutenberg.org/files/26998/26998-h/26998-h.htm","image/jpeg":"https://www.gutenberg.org/cache/epub/26998/pg26998.cover.medium.jpg","text/html":"https://www.gutenberg.org/ebooks/26998.html.images","application/rdf+xml":"https://www.gutenberg.org/ebooks/26998.rdf","application/x-mobipocket-ebook":"https://www.gutenberg.org/ebooks/26998.kindle.images","application/epub+zip":"https://www.gutenberg.org/ebooks/26998.epub.images","text/plain":"https://www.gutenberg.org/ebooks/26998.txt.utf-8"},"download_count":377}