{"id":15381,"title":"Victorian Short Stories: Stories of Courtship","authors":[],"translators":[],"subjects":["Courtship -- Fiction","Short stories"],"bookshelves":["Short Stories"],"languages":["en"],"copyright":false,"media_type":"Text","formats":{"application/octet-stream":"https://www.gutenberg.org/files/15381/15381-h.zip","text/plain; charset=us-ascii":"https://www.gutenberg.org/files/15381/15381.zip","image/jpeg":"https://www.gutenberg.org/cache/epub/15381/pg15381.cover.medium.jpg","text/html":"https://www.gutenberg.org/ebooks/15381.html.images","text/plain; charset=iso-8859-1":"https://www.gutenberg.org/files/15381/15381-8.txt","text/plain":"https://www.gutenberg.org/ebooks/15381.txt.utf-8","application/epub+zip":"https://www.gutenberg.org/ebooks/15381.epub.images","application/rdf+xml":"https://www.gutenberg.org/ebooks/15381.rdf","application/x-mobipocket-ebook":"https://www.gutenberg.org/ebooks/15381.kindle.images"},"download_count":301}