{"id":8299,"title":"Filipino Popular Tales","authors":[],"translators":[],"subjects":["Folklore -- Philippines","Tales -- Philippines"],"bookshelves":["Folklore"],"languages":["en"],"copyright":false,"media_type":"Text","formats":{"application/zip":"https://www.gutenberg.org/files/8299/8299.zip","text/plain; charset=iso-8859-1":"https://www.gutenberg.org/files/8299/8299-8.zip","text/plain; charset=us-ascii":"https://www.gutenberg.org/files/8299/8299.txt","text/html; charset=iso-8859-1":"https://www.gutenberg.org/files/8299/8299-h.zip","image/jpeg":"https://www.gutenberg.org/cache/epub/8299/pg8299.cover.medium.jpg","text/html":"https://www.gutenberg.org/ebooks/8299.html.images","text/plain":"https://www.gutenberg.org/ebooks/8299.txt.utf-8","application/x-mobipocket-ebook":"https://www.gutenberg.org/ebooks/8299.kindle.images","application/rdf+xml":"https://www.gutenberg.org/ebooks/8299.rdf","application/epub+zip":"https://www.gutenberg.org/ebooks/8299.epub.images"},"download_count":489}