{"id":22976,"title":"Slave Narratives: A Folk History of Slavery in the United States from Interviews with Former Slaves, Volume XI, North Carolina Narratives, Part 1","authors":[{"name":"United States. Work Projects Administration","birth_year":null,"death_year":null}],"translators":[],"subjects":["African Americans -- North Carolina -- Biography","North Carolina -- History -- 1775-1865 -- Biography","Slave narratives -- North Carolina","Slavery -- North Carolina","Slaves -- North Carolina -- Biography","Slaves -- North Carolina -- Social conditions"],"bookshelves":["Slavery"],"languages":["en"],"copyright":false,"media_type":"Text","formats":{"image/jpeg":"https://www.gutenberg.org/cache/epub/22976/pg22976.cover.small.jpg","application/zip":"https://www.gutenberg.org/files/22976/22976.zip","text/html; charset=iso-8859-1":"https://www.gutenberg.org/files/22976/22976-h/22976-h.htm","text/plain; charset=us-ascii":"https://www.gutenberg.org/files/22976/22976.txt","text/html":"https://www.gutenberg.org/ebooks/22976.html.images","text/plain":"https://www.gutenberg.org/ebooks/22976.txt.utf-8","application/epub+zip":"https://www.gutenberg.org/ebooks/22976.epub.images","application/rdf+xml":"https://www.gutenberg.org/ebooks/22976.rdf","application/x-mobipocket-ebook":"https://www.gutenberg.org/ebooks/22976.kindle.images"},"download_count":422}