{"id":3031,"title":"Wild Animals I Have Known","authors":[{"name":"Seton, Ernest Thompson","birth_year":1860,"death_year":1946}],"translators":[],"subjects":["Animals -- Anecdotes","Animals -- Biography"],"bookshelves":["Canada","Children's Instructional Books"],"languages":["en"],"copyright":false,"media_type":"Text","formats":{"text/plain; charset=us-ascii":"https://www.gutenberg.org/files/3031/3031.txt","text/html; charset=us-ascii":"https://www.gutenberg.org/files/3031/3031-h.zip","image/jpeg":"https://www.gutenberg.org/cache/epub/3031/pg3031.cover.small.jpg","text/html":"https://www.gutenberg.org/ebooks/3031.html.images","application/rdf+xml":"https://www.gutenberg.org/ebooks/3031.rdf","application/epub+zip":"https://www.gutenberg.org/ebooks/3031.epub.images","application/x-mobipocket-ebook":"https://www.gutenberg.org/ebooks/3031.kindle.images","text/plain":"https://www.gutenberg.org/ebooks/3031.txt.utf-8"},"download_count":370}