{"id":59432,"title":"Plays","authors":[{"name":"Glaspell, Susan","birth_year":1876,"death_year":1948}],"translators":[],"subjects":["American drama"],"bookshelves":[],"languages":["en"],"copyright":false,"media_type":"Text","formats":{"image/jpeg":"https://www.gutenberg.org/cache/epub/59432/pg59432.cover.small.jpg","text/html; charset=utf-8":"https://www.gutenberg.org/files/59432/59432-h/59432-h.htm","text/plain; charset=utf-8":"https://www.gutenberg.org/files/59432/59432-0.txt","text/html":"https://www.gutenberg.org/ebooks/59432.html.images","application/x-mobipocket-ebook":"https://www.gutenberg.org/ebooks/59432.kindle.images","application/rdf+xml":"https://www.gutenberg.org/ebooks/59432.rdf","application/epub+zip":"https://www.gutenberg.org/ebooks/59432.epub.images"},"download_count":295}