{"id":11666,"title":"The Conjure Woman","authors":[{"name":"Chesnutt, Charles W. (Charles Waddell)","birth_year":1858,"death_year":1932}],"translators":[],"subjects":["African Americans -- Fiction","Southern States -- Social life and customs -- Fiction"],"bookshelves":["African American Writers"],"languages":["en"],"copyright":false,"media_type":"Text","formats":{"text/html":"https://www.gutenberg.org/files/11666/11666-h.zip","application/zip":"https://www.gutenberg.org/files/11666/11666.zip","image/jpeg":"https://www.gutenberg.org/cache/epub/11666/pg11666.cover.medium.jpg","text/plain; charset=us-ascii":"https://www.gutenberg.org/files/11666/11666.txt","text/plain":"https://www.gutenberg.org/ebooks/11666.txt.utf-8","application/epub+zip":"https://www.gutenberg.org/ebooks/11666.epub.images","application/rdf+xml":"https://www.gutenberg.org/ebooks/11666.rdf","text/html; charset=us-ascii":"https://www.gutenberg.org/files/11666/11666-h/11666-h.htm","application/x-mobipocket-ebook":"https://www.gutenberg.org/ebooks/11666.kindle.images"},"download_count":595}