{"id":58985,"title":"The Babees' Book: Medieval Manners for the Young: Done into Modern English","authors":[],"translators":[{"name":"Naylor, L. J.","birth_year":null,"death_year":null}],"subjects":["Child rearing","Children -- Conduct of life","Conduct of life","Education","Education -- England","England -- Social life and customs","Etiquette for children and teenagers","Etiquette, Medieval","Home economics -- England","Table"],"bookshelves":[],"languages":["en"],"copyright":false,"media_type":"Text","formats":{"text/html; charset=utf-8":"https://www.gutenberg.org/files/58985/58985-h.zip","text/plain; charset=utf-8":"https://www.gutenberg.org/files/58985/58985-0.zip","image/jpeg":"https://www.gutenberg.org/cache/epub/58985/pg58985.cover.medium.jpg","text/html":"https://www.gutenberg.org/ebooks/58985.html.images","application/rdf+xml":"https://www.gutenberg.org/ebooks/58985.rdf","application/epub+zip":"https://www.gutenberg.org/ebooks/58985.epub.images","application/x-mobipocket-ebook":"https://www.gutenberg.org/ebooks/58985.kindle.images"},"download_count":264}