{"id":3285,"title":"The Deerslayer","authors":[{"name":"Cooper, James Fenimore","birth_year":1789,"death_year":1851}],"translators":[],"subjects":["Bildungsromans","Bumppo, Natty (Fictitious character) -- Fiction","Delaware Indians -- Fiction","Frontier and pioneer life -- Fiction","Historical fiction","Hunters -- Fiction","Male friendship -- Fiction","New York (State) -- History -- French and Indian War, 1754-1763 -- Fiction","Scouting (Reconnaissance) -- Fiction","War stories"],"bookshelves":["Native America"],"languages":["en"],"copyright":false,"media_type":"Text","formats":{"text/html; charset=utf-8":"https://www.gutenberg.org/files/3285/3285-h/3285-h.htm","application/zip":"https://www.gutenberg.org/files/3285/3285-8.zip","image/jpeg":"https://www.gutenberg.org/cache/epub/3285/pg3285.cover.small.jpg","text/plain; charset=utf-8":"https://www.gutenberg.org/files/3285/3285-0.txt","text/plain; charset=us-ascii":"https://www.gutenberg.org/files/3285/3285.txt","text/plain; charset=iso-8859-1":"https://www.gutenberg.org/files/3285/3285-8.txt","text/html":"https://www.gutenberg.org/ebooks/3285.html.images","application/x-mobipocket-ebook":"https://www.gutenberg.org/ebooks/3285.kindle.images","application/epub+zip":"https://www.gutenberg.org/ebooks/3285.epub.images","application/rdf+xml":"https://www.gutenberg.org/ebooks/3285.rdf"},"download_count":349}