{"id":37027,"title":"With Fire and Sword: An Historical Novel of Poland and Russia","authors":[{"name":"Sienkiewicz, Henryk","birth_year":1846,"death_year":1916}],"translators":[{"name":"Curtin, Jeremiah","birth_year":1835,"death_year":1906}],"subjects":["Cossacks -- Poland -- Fiction","Cossacks -- Ukraine -- Fiction","Historical fiction","Poland -- History -- John II Casimir, 1648-1668 -- Fiction"],"bookshelves":[],"languages":["en"],"copyright":false,"media_type":"Text","formats":{"application/zip":"https://www.gutenberg.org/files/37027/37027-0.zip","text/html":"https://www.gutenberg.org/ebooks/37027.html.images","image/jpeg":"https://www.gutenberg.org/cache/epub/37027/pg37027.cover.small.jpg","text/plain; charset=us-ascii":"https://www.gutenberg.org/files/37027/37027-0.txt","application/rdf+xml":"https://www.gutenberg.org/ebooks/37027.rdf","application/epub+zip":"https://www.gutenberg.org/ebooks/37027.epub.images","application/x-mobipocket-ebook":"https://www.gutenberg.org/ebooks/37027.kindle.images","text/plain":"https://www.gutenberg.org/ebooks/37027.txt.utf-8"},"download_count":309}