{"id":15015,"title":"Sex and Society: Studies in the Social Psychology of Sex","authors":[{"name":"Thomas, William Isaac","birth_year":1863,"death_year":1947}],"translators":[],"subjects":["Sex","Women -- Social and moral questions","Women -- Social conditions"],"bookshelves":[],"languages":["en"],"copyright":false,"media_type":"Text","formats":{"text/plain; charset=iso-8859-1":"https://www.gutenberg.org/files/15015/15015-8.zip","application/zip":"https://www.gutenberg.org/files/15015/15015.zip","text/html; charset=iso-8859-1":"https://www.gutenberg.org/files/15015/15015-h/15015-h.htm","image/jpeg":"https://www.gutenberg.org/cache/epub/15015/pg15015.cover.small.jpg","text/html":"https://www.gutenberg.org/ebooks/15015.html.images","text/plain":"https://www.gutenberg.org/ebooks/15015.txt.utf-8","application/epub+zip":"https://www.gutenberg.org/ebooks/15015.epub.images","application/rdf+xml":"https://www.gutenberg.org/ebooks/15015.rdf","application/x-mobipocket-ebook":"https://www.gutenberg.org/ebooks/15015.kindle.images","text/plain; charset=us-ascii":"https://www.gutenberg.org/files/15015/15015.txt"},"download_count":266}