{"id":67568,"title":"Peaks of Shala","authors":[{"name":"Lane, Rose Wilder","birth_year":1886,"death_year":1968}],"translators":[],"subjects":["Albania -- Description and travel","Albania -- Social life and customs","Lane, Rose Wilder, 1886-1968"],"bookshelves":[],"languages":["en"],"copyright":false,"media_type":"Text","formats":{"application/rdf+xml":"https://www.gutenberg.org/ebooks/67568.rdf","image/jpeg":"https://www.gutenberg.org/cache/epub/67568/pg67568.cover.medium.jpg","text/plain":"https://www.gutenberg.org/ebooks/67568.txt.utf-8","application/epub+zip":"https://www.gutenberg.org/ebooks/67568.epub.images","application/x-mobipocket-ebook":"https://www.gutenberg.org/ebooks/67568.kindle.images","text/html":"https://www.gutenberg.org/files/67568/67568-h/67568-h.htm","application/octet-stream":"https://www.gutenberg.org/files/67568/67568-0.zip","text/plain; charset=us-ascii":"https://www.gutenberg.org/files/67568/67568-0.txt","application/zip":"https://www.gutenberg.org/files/67568/67568-h.zip"},"download_count":810}